redgifdl/__init__.py
redgifdl/__main__.py
redgifdl/download.py
redgifdl-0.1.9.dist-info/METADATA
redgifdl-0.1.9.dist-info/WHEEL
redgifdl-0.1.9.dist-info/RECORD
